BertEmbeddings/__init__.py
bert_embeddings-0.0.8.dist-info/LICENSE
bert_embeddings-0.0.8.dist-info/METADATA
bert_embeddings-0.0.8.dist-info/WHEEL
bert_embeddings-0.0.8.dist-info/top_level.txt
bert_embeddings-0.0.8.dist-info/RECORD
